easyweb3/__init__.py
easyweb3/easyweb3.py
easyweb3-1.2308.0.dist-info/LICENSE
easyweb3-1.2308.0.dist-info/METADATA
easyweb3-1.2308.0.dist-info/WHEEL
easyweb3-1.2308.0.dist-info/top_level.txt
easyweb3-1.2308.0.dist-info/RECORD
